skg_main/__init__.py
skg_main/autotwin_connector.py
skg_main/resources/config/config.ini
skg_main/resources/config/local.ini
skg_main/resources/config/sha.json
skg_main/resources/schemas/croma.json
skg_main/resources/schemas/legoFactory.json
skg_main/resources/schemas/pizzaLineV1.json
skg_main/resources/schemas/pizzaLineV2.json
skg_main/resources/schemas/pizzaLineV3.json
skg_main/resources/schemas/pizzaLineV4.json
skg_main/skg_logger/__init__.py
skg_main/skg_logger/__pycache__/__init__.cpython-310.pyc
skg_main/skg_logger/__pycache__/logger.cpython-310.pyc
skg_main/skg_logger/logger.py
skg_main/skg_mgrs/__init__.py
skg_main/skg_mgrs/__pycache__/__init__.cpython-310.pyc
skg_main/skg_mgrs/__pycache__/connector_mgr.cpython-310.pyc
skg_main/skg_mgrs/__pycache__/skg_reader.cpython-310.pyc
skg_main/skg_mgrs/__pycache__/skg_writer.cpython-310.pyc
skg_main/skg_mgrs/connector_mgr.py
skg_main/skg_mgrs/skg_reader.py
skg_main/skg_mgrs/skg_writer.py
skg_main/skg_model/__init__.py
skg_main/skg_model/__pycache__/__init__.cpython-310.pyc
skg_main/skg_model/__pycache__/automata.cpython-310.pyc
skg_main/skg_model/__pycache__/schema.cpython-310.pyc
skg_main/skg_model/__pycache__/semantics.cpython-310.pyc
skg_main/skg_model/automata.py
skg_main/skg_model/schema.py
skg_main/skg_model/semantics.py
skg_connector-0.1.16.dist-info/LICENSE.md
skg_connector-0.1.16.dist-info/METADATA
skg_connector-0.1.16.dist-info/WHEEL
skg_connector-0.1.16.dist-info/RECORD
