Metadata-Version: 2.3
Name: skg-connector
Version: 0.1.16
Summary: Module to extract and store data into an SKG
Author: livialestingi
Author-email: livia.lestingi@polimi.it
Requires-Python: >=3.10,<4.0
Classifier: Development Status :: 1 - Planning
Classifier: Intended Audience :: Manufacturing
Classifier: License :: OSI Approved :: BSD License
Classifier: Operating System :: OS Independent
Classifier: Programming Language :: Python :: 3
Classifier: Programming Language :: Python :: 3.10
Classifier: Programming Language :: Python :: 3.11
Classifier: Programming Language :: Python :: 3.12
Classifier: Programming Language :: Python :: 3.13
Classifier: Programming Language :: Python :: 3 :: Only
Requires-Dist: graphviz (>=0.20.1,<0.21.0)
Requires-Dist: neo4j (>=5.17.0,<6.0.0)
Requires-Dist: pygraphviz (>=1.12,<2.0)
Project-URL: Homepage, https://github.com/LesLivia/skg_connector
